Workbook

Sheet Painel
A1: Painel do mês
A2: Troque o mês na célula amarela (use o dia 1, ex.: 01/11/2026). O resto é automático.
A4: Mês | B4: =Configurações!$B$4 -> 46296 | C4: (fórmula inicial = mês de Configurações; pode sobrescrever com uma data)
A6: Categoria | B6: Tipo | C6: Previsto | D6: Realizado | E6: Diferença | F6: % do previsto
A7: =IF(Configurações!A7="","",Configurações!A7) -> Salário | B7: =IF(Configurações!B7="","",Configurações!B7) -> Ganho | C7: =IF($A7="","",N(Configurações!C7)) -> 0 | D7: =IF($A7="","",SUMIFS(Lançamentos!$D$5:$D$2004,Lançamentos!$B$5:$B$2004,$A7,Lançamentos!$H$5:$H$2004,$B$4)) -> 0 | E7: =IF($A7="","",IF($B7="Ganho",D7-C7,C7-D7)) -> 0 | F7: =IF(OR($A7="",N(C7)=0),"",D7/C7)
A8: =IF(Configurações!A8="","",Configurações!A8) -> Renda variável | B8: =IF(Configurações!B8="","",Configurações!B8) -> Ganho | C8: =IF($A8="","",N(Configurações!C8)) -> 0 | D8: =IF($A8="","",SUMIFS(Lançamentos!$D$5:$D$2004,Lançamentos!$B$5:$B$2004,$A8,Lançamentos!$H$5:$H$2004,$B$4)) -> 0 | E8: =IF($A8="","",IF($B8="Ganho",D8-C8,C8-D8)) -> 0 | F8: =IF(OR($A8="",N(C8)=0),"",D8/C8)
A9: =IF(Configurações!A9="","",Configurações!A9) -> Outros ganhos | B9: =IF(Configurações!B9="","",Configurações!B9) -> Ganho | C9: =IF($A9="","",N(Configurações!C9)) -> 0 | D9: =IF($A9="","",SUMIFS(Lançamentos!$D$5:$D$2004,Lançamentos!$B$5:$B$2004,$A9,Lançamentos!$H$5:$H$2004,$B$4)) -> 0 | E9: =IF($A9="","",IF($B9="Ganho",D9-C9,C9-D9)) -> 0 | F9: =IF(OR($A9="",N(C9)=0),"",D9/C9)
A10: =IF(Configurações!A10="","",Configurações!A10) -> Aluguel | B10: =IF(Configurações!B10="","",Configurações!B10) -> Gasto | C10: =IF($A10="","",N(Configurações!C10)) -> 0 | D10: =IF($A10="","",SUMIFS(Lançamentos!$D$5:$D$2004,Lançamentos!$B$5:$B$2004,$A10,Lançamentos!$H$5:$H$2004,$B$4)) -> 0 | E10: =IF($A10="","",IF($B10="Ganho",D10-C10,C10-D10)) -> 0 | F10: =IF(OR($A10="",N(C10)=0),"",D10/C10)
A11: =IF(Configurações!A11="","",Configurações!A11) -> Luz | B11: =IF(Configurações!B11="","",Configurações!B11) -> Gasto | C11: =IF($A11="","",N(Configurações!C11)) -> 0 | D11: =IF($A11="","",SUMIFS(Lançamentos!$D$5:$D$2004,Lançamentos!$B$5:$B$2004,$A11,Lançamentos!$H$5:$H$2004,$B$4)) -> 0 | E11: =IF($A11="","",IF($B11="Ganho",D11-C11,C11-D11)) -> 0 | F11: =IF(OR($A11="",N(C11)=0),"",D11/C11)
A12: =IF(Configurações!A12="","",Configurações!A12) -> Água | B12: =IF(Configurações!B12="","",Configurações!B12) -> Gasto | C12: =IF($A12="","",N(Configurações!C12)) -> 0 | D12: =IF($A12="","",SUMIFS(Lançamentos!$D$5:$D$2004,Lançamentos!$B$5:$B$2004,$A12,Lançamentos!$H$5:$H$2004,$B$4)) -> 0 | E12: =IF($A12="","",IF($B12="Ganho",D12-C12,C12-D12)) -> 0 | F12: =IF(OR($A12="",N(C12)=0),"",D12/C12)
A13: =IF(Configurações!A13="","",Configurações!A13) -> Compras de casa | B13: =IF(Configurações!B13="","",Configurações!B13) -> Gasto | C13: =IF($A13="","",N(Configurações!C13)) -> 0 | D13: =IF($A13="","",SUMIFS(Lançamentos!$D$5:$D$2004,Lançamentos!$B$5:$B$2004,$A13,Lançamentos!$H$5:$H$2004,$B$4)) -> 0 | E13: =IF($A13="","",IF($B13="Ganho",D13-C13,C13-D13)) -> 0 | F13: =IF(OR($A13="",N(C13)=0),"",D13/C13)
A14: =IF(Configurações!A14="","",Configurações!A14) -> Alimentação na rua | B14: =IF(Configurações!B14="","",Configurações!B14) -> Gasto | C14: =IF($A14="","",N(Configurações!C14)) -> 0 | D14: =IF($A14="","",SUMIFS(Lançamentos!$D$5:$D$2004,Lançamentos!$B$5:$B$2004,$A14,Lançamentos!$H$5:$H$2004,$B$4)) -> 0 | E14: =IF($A14="","",IF($B14="Ganho",D14-C14,C14-D14)) -> 0 | F14: =IF(OR($A14="",N(C14)=0),"",D14/C14)
A15: =IF(Configurações!A15="","",Configurações!A15) -> iFood | B15: =IF(Configurações!B15="","",Configurações!B15) -> Gasto | C15: =IF($A15="","",N(Configurações!C15)) -> 0 | D15: =IF($A15="","",SUMIFS(Lançamentos!$D$5:$D$2004,Lançamentos!$B$5:$B$2004,$A15,Lançamentos!$H$5:$H$2004,$B$4)) -> 62.9 | E15: =IF($A15="","",IF($B15="Ganho",D15-C15,C15-D15)) -> -62.9 | F15: =IF(OR($A15="",N(C15)=0),"",D15/C15)
A16: =IF(Configurações!A16="","",Configurações!A16) -> Bar | B16: =IF(Configurações!B16="","",Configurações!B16) -> Gasto | C16: =IF($A16="","",N(Configurações!C16)) -> 0 | D16: =IF($A16="","",SUMIFS(Lançamentos!$D$5:$D$2004,Lançamentos!$B$5:$B$2004,$A16,Lançamentos!$H$5:$H$2004,$B$4)) -> 0 | E16: =IF($A16="","",IF($B16="Ganho",D16-C16,C16-D16)) -> 0 | F16: =IF(OR($A16="",N(C16)=0),"",D16/C16)
A17: =IF(Configurações!A17="","",Configurações!A17) -> Transporte | B17: =IF(Configurações!B17="","",Configurações!B17) -> Gasto | C17: =IF($A17="","",N(Configurações!C17)) -> 0 | D17: =IF($A17="","",SUMIFS(Lançamentos!$D$5:$D$2004,Lançamentos!$B$5:$B$2004,$A17,Lançamentos!$H$5:$H$2004,$B$4)) -> 0 | E17: =IF($A17="","",IF($B17="Ganho",D17-C17,C17-D17)) -> 0 | F17: =IF(OR($A17="",N(C17)=0),"",D17/C17)
A18: =IF(Configurações!A18="","",Configurações!A18) -> Internet/Celular | B18: =IF(Configurações!B18="","",Configurações!B18) -> Gasto | C18: =IF($A18="","",N(Configurações!C18)) -> 0 | D18: =IF($A18="","",SUMIFS(Lançamentos!$D$5:$D$2004,Lançamentos!$B$5:$B$2004,$A18,Lançamentos!$H$5:$H$2004,$B$4)) -> 0 | E18: =IF($A18="","",IF($B18="Ganho",D18-C18,C18-D18)) -> 0 | F18: =IF(OR($A18="",N(C18)=0),"",D18/C18)
... A30: =IF(Configurações!A30="","",Configurações!A30) | B30: =IF(Configurações!B30="","",Configurações!B30) | C30: =IF($A30="","",N(Configurações!C30)) | D30: =IF($A30="","",SUMIFS(Lançamentos!$D$5:$D$2004,Lançamentos!$B$5:$B$2004,$A30,Lançamentos!$H$5:$H$2004,$B$4)) | E30: =IF($A30="","",IF($B30="Ganho",D30-C30,C30-D30)) | F30: =IF(OR($A30="",N(C30)=0),"",D30/C30)
A32: Resumo | C32: Previsto | D32: Realizado
A33: Ganhos do mês | C33: =SUMIFS(C7:C30,B7:B30,"Ganho") -> 0 | D33: =SUMIFS(D7:D30,B7:B30,"Ganho") -> 0
A34: Gastos do mês | C34: =SUMIFS(C7:C30,B7:B30,"Gasto") -> 0 | D34: =SUMIFS(D7:D30,B7:B30,"Gasto") -> 62.9
A35: SOBROU NO MÊS | C35: =C33-C34 -> 0 | D35: =D33-D34 -> -62.9
A37: Gasto com rua + iFood + bar no mês | D37: =SUMIFS(D7:D30,A7:A30,"Alimentação na rua")+SUMIFS(D7:D30,A7:A30,"iFood")+SUMIFS(D7:D30,A7:A30,"Bar") -> 62.9
A38: % dos ganhos que foi pra isso | D38: =IF(D33=0,"",D37/D33)
A40: Como usar
A41: 1. Em Configurações: preencha salário, renda variável prevista e quanto quer gastar por categoria.
A42: 2. Em Lançamentos: cada ganho ou gasto vira uma linha (data, categoria, descrição, valor).
A43: 3. Toda semana: lance tudo e confira a aba Resumo Semanal.
A44: 4. Aqui no Painel: troque o mês e veja previsto x realizado. Vermelho = estourou.
A45: Células amarelas/texto azul = você preenche. O resto é fórmula, não precisa mexer.

Sheet Configurações
A1: Configurações
A2: Células amarelas = você preenche. Categorias novas: escreva nas linhas vazias da tabela.
A4: Mês inicial da planilha | B4: 46296 | C4: Primeiro mês que aparece nos resumos (12 meses a partir dele).
A6: Categoria | B6: Tipo | C6: Previsto por mês (R$) | D6: Observação
A7: Salário | B7: Ganho | D7: Valor líquido que cai na conta
A8: Renda variável | B8: Ganho | D8: Quanto você prevê de renda variável no mês
A9: Outros ganhos | B9: Ganho
A10: Aluguel | B10: Gasto
A11: Luz | B11: Gasto
A12: Água | B12: Gasto
A13: Compras de casa | B13: Gasto | D13: Mercado, limpeza, itens de casa
A14: Alimentação na rua | B14: Gasto | D14: Restaurante, lanche, padaria
A15: iFood | B15: Gasto | D15: Delivery
A16: Bar | B16: Gasto | D16: Conta de bar / rolê
A17: Transporte | B17: Gasto | D17: Uber, combustível, ônibus
A18: Internet/Celular | B18: Gasto
A19: Assinaturas | B19: Gasto | D19: Streaming, apps
A20: Saúde | B20: Gasto | D20: Farmácia, plano, academia
A21: Lazer | B21: Gasto
A22: Outros gastos | B22: Gasto
A32: Total ganhos previstos | C32: =SUMIFS(C7:C30,B7:B30,"Ganho") -> 0
A33: Total gastos previstos | C33: =SUMIFS(C7:C30,B7:B30,"Gasto") -> 0
A34: Sobra prevista no mês | C34: =C32-C33 -> 0

Sheet Lançamentos
A1: Lançamentos
A2: Preencha só as colunas amarelas (A–E). Tipo, Semana e Mês são automáticos. A linha 5 é um exemplo — pode apagar.
A4: Data | B4: Categoria | C4: Descrição | D4: Valor (R$) | E4: Forma de pagamento | F4: Tipo | G4: Semana (seg.) | H4: Mês
A5: 46305 | B5: iFood | C5: Pizza sábado (exemplo – pode apagar) | D5: 62.9 | E5: Crédito | F5: =IF(B5="","",IFERROR(INDEX(Configurações!$B$7:$B$30,MATCH(B5,Configurações!$A$7:$A$30,0)),"?")) -> Gasto | G5: =IF(A5="","",A5-WEEKDAY(A5,2)+1) -> 46300 | H5: =IF(A5="","",DATE(YEAR(A5),MONTH(A5),1)) -> 46296
F6: =IF(B6="","",IFERROR(INDEX(Configurações!$B$7:$B$30,MATCH(B6,Configurações!$A$7:$A$30,0)),"?")) | G6: =IF(A6="","",A6-WEEKDAY(A6,2)+1) | H6: =IF(A6="","",DATE(YEAR(A6),MONTH(A6),1))
F7: =IF(B7="","",IFERROR(INDEX(Configurações!$B$7:$B$30,MATCH(B7,Configurações!$A$7:$A$30,0)),"?")) | G7: =IF(A7="","",A7-WEEKDAY(A7,2)+1) | H7: =IF(A7="","",DATE(YEAR(A7),MONTH(A7),1))
F8: =IF(B8="","",IFERROR(INDEX(Configurações!$B$7:$B$30,MATCH(B8,Configurações!$A$7:$A$30,0)),"?")) | G8: =IF(A8="","",A8-WEEKDAY(A8,2)+1) | H8: =IF(A8="","",DATE(YEAR(A8),MONTH(A8),1))
F9: =IF(B9="","",IFERROR(INDEX(Configurações!$B$7:$B$30,MATCH(B9,Configurações!$A$7:$A$30,0)),"?")) | G9: =IF(A9="","",A9-WEEKDAY(A9,2)+1) | H9: =IF(A9="","",DATE(YEAR(A9),MONTH(A9),1))
F10: =IF(B10="","",IFERROR(INDEX(Configurações!$B$7:$B$30,MATCH(B10,Configurações!$A$7:$A$30,0)),"?")) | G10: =IF(A10="","",A10-WEEKDAY(A10,2)+1) | H10: =IF(A10="","",DATE(YEAR(A10),MONTH(A10),1))
F11: =IF(B11="","",IFERROR(INDEX(Configurações!$B$7:$B$30,MATCH(B11,Configurações!$A$7:$A$30,0)),"?")) | G11: =IF(A11="","",A11-WEEKDAY(A11,2)+1) | H11: =IF(A11="","",DATE(YEAR(A11),MONTH(A11),1))
F12: =IF(B12="","",IFERROR(INDEX(Configurações!$B$7:$B$30,MATCH(B12,Configurações!$A$7:$A$30,0)),"?")) | G12: =IF(A12="","",A12-WEEKDAY(A12,2)+1) | H12: =IF(A12="","",DATE(YEAR(A12),MONTH(A12),1))
F13: =IF(B13="","",IFERROR(INDEX(Configurações!$B$7:$B$30,MATCH(B13,Configurações!$A$7:$A$30,0)),"?")) | G13: =IF(A13="","",A13-WEEKDAY(A13,2)+1) | H13: =IF(A13="","",DATE(YEAR(A13),MONTH(A13),1))
F14: =IF(B14="","",IFERROR(INDEX(Configurações!$B$7:$B$30,MATCH(B14,Configurações!$A$7:$A$30,0)),"?")) | G14: =IF(A14="","",A14-WEEKDAY(A14,2)+1) | H14: =IF(A14="","",DATE(YEAR(A14),MONTH(A14),1))
F15: =IF(B15="","",IFERROR(INDEX(Configurações!$B$7:$B$30,MATCH(B15,Configurações!$A$7:$A$30,0)),"?")) | G15: =IF(A15="","",A15-WEEKDAY(A15,2)+1) | H15: =IF(A15="","",DATE(YEAR(A15),MONTH(A15),1))
F16: =IF(B16="","",IFERROR(INDEX(Configurações!$B$7:$B$30,MATCH(B16,Configurações!$A$7:$A$30,0)),"?")) | G16: =IF(A16="","",A16-WEEKDAY(A16,2)+1) | H16: =IF(A16="","",DATE(YEAR(A16),MONTH(A16),1))
F17: =IF(B17="","",IFERROR(INDEX(Configurações!$B$7:$B$30,MATCH(B17,Configurações!$A$7:$A$30,0)),"?")) | G17: =IF(A17="","",A17-WEEKDAY(A17,2)+1) | H17: =IF(A17="","",DATE(YEAR(A17),MONTH(A17),1))
... F2004: =IF(B2004="","",IFERROR(INDEX(Configurações!$B$7:$B$30,MATCH(B2004,Configurações!$A$7:$A$30,0)),"?")) | G2004: =IF(A2004="","",A2004-WEEKDAY(A2004,2)+1) | H2004: =IF(A2004="","",DATE(YEAR(A2004),MONTH(A2004),1))

Sheet Resumo Mensal
A1: Resumo mensal
A2: Tudo automático. Previsto vem de Configurações; os meses somam os Lançamentos.
A4: Categoria | B4: Tipo | C4: Previsto/mês | D4: =Configurações!$B$4 -> 46296 | E4: =EDATE(D4,1) -> 46327 | F4: =EDATE(E4,1) -> 46357 | G4: =EDATE(F4,1) -> 46388 | H4: =EDATE(G4,1) -> 46419 | I4: =EDATE(H4,1) -> 46447 | J4: =EDATE(I4,1) -> 46478 | K4: =EDATE(J4,1) -> 46508 | L4: =EDATE(K4,1) -> 46539 | ... O4: =EDATE(N4,1) -> 46631 | P4: Total 12 meses | Q4: Média mensal
A5: =IF(Configurações!A7="","",Configurações!A7) -> Salário | B5: =IF(Configurações!B7="","",Configurações!B7) -> Ganho | C5: =IF($A5="","",Configurações!C7) -> 0 | D5: =IF($A5="","",SUMIFS(Lançamentos!$D$5:$D$2004,Lançamentos!$B$5:$B$2004,$A5,Lançamentos!$H$5:$H$2004,D$4)) -> 0 | E5: =IF($A5="","",SUMIFS(Lançamentos!$D$5:$D$2004,Lançamentos!$B$5:$B$2004,$A5,Lançamentos!$H$5:$H$2004,E$4)) -> 0 | F5: =IF($A5="","",SUMIFS(Lançamentos!$D$5:$D$2004,Lançamentos!$B$5:$B$2004,$A5,Lançamentos!$H$5:$H$2004,F$4)) -> 0 | G5: =IF($A5="","",SUMIFS(Lançamentos!$D$5:$D$2004,Lançamentos!$B$5:$B$2004,$A5,Lançamentos!$H$5:$H$2004,G$4)) -> 0 | H5: =IF($A5="","",SUMIFS(Lançamentos!$D$5:$D$2004,Lançamentos!$B$5:$B$2004,$A5,Lançamentos!$H$5:$H$2004,H$4)) -> 0 | I5: =IF($A5="","",SUMIFS(Lançamentos!$D$5:$D$2004,Lançamentos!$B$5:$B$2004,$A5,Lançamentos!$H$5:$H$2004,I$4)) -> 0 | J5: =IF($A5="","",SUMIFS(Lançamentos!$D$5:$D$2004,Lançamentos!$B$5:$B$2004,$A5,Lançamentos!$H$5:$H$2004,J$4)) -> 0 | K5: =IF($A5="","",SUMIFS(Lançamentos!$D$5:$D$2004,Lançamentos!$B$5:$B$2004,$A5,Lançamentos!$H$5:$H$2004,K$4)) -> 0 | ... O5: =IF($A5="","",SUMIFS(Lançamentos!$D$5:$D$2004,Lançamentos!$B$5:$B$2004,$A5,Lançamentos!$H$5:$H$2004,O$4)) -> 0 | P5: =IF($A5="","",SUM(D5:O5)) -> 0 | Q5: =IF($A5="","",P5/12) -> 0
A6: =IF(Configurações!A8="","",Configurações!A8) -> Renda variável | B6: =IF(Configurações!B8="","",Configurações!B8) -> Ganho | C6: =IF($A6="","",Configurações!C8) -> 0 | D6: =IF($A6="","",SUMIFS(Lançamentos!$D$5:$D$2004,Lançamentos!$B$5:$B$2004,$A6,Lançamentos!$H$5:$H$2004,D$4)) -> 0 | E6: =IF($A6="","",SUMIFS(Lançamentos!$D$5:$D$2004,Lançamentos!$B$5:$B$2004,$A6,Lançamentos!$H$5:$H$2004,E$4)) -> 0 | F6: =IF($A6="","",SUMIFS(Lançamentos!$D$5:$D$2004,Lançamentos!$B$5:$B$2004,$A6,Lançamentos!$H$5:$H$2004,F$4)) -> 0 | G6: =IF($A6="","",SUMIFS(Lançamentos!$D$5:$D$2004,Lançamentos!$B$5:$B$2004,$A6,Lançamentos!$H$5:$H$2004,G$4)) -> 0 | H6: =IF($A6="","",SUMIFS(Lançamentos!$D$5:$D$2004,Lançamentos!$B$5:$B$2004,$A6,Lançamentos!$H$5:$H$2004,H$4)) -> 0 | I6: =IF($A6="","",SUMIFS(Lançamentos!$D$5:$D$2004,Lançamentos!$B$5:$B$2004,$A6,Lançamentos!$H$5:$H$2004,I$4)) -> 0 | J6: =IF($A6="","",SUMIFS(Lançamentos!$D$5:$D$2004,Lançamentos!$B$5:$B$2004,$A6,Lançamentos!$H$5:$H$2004,J$4)) -> 0 | K6: =IF($A6="","",SUMIFS(Lançamentos!$D$5:$D$2004,Lançamentos!$B$5:$B$2004,$A6,Lançamentos!$H$5:$H$2004,K$4)) -> 0 | ... O6: =IF($A6="","",SUMIFS(Lançamentos!$D$5:$D$2004,Lançamentos!$B$5:$B$2004,$A6,Lançamentos!$H$5:$H$2004,O$4)) -> 0 | P6: =IF($A6="","",SUM(D6:O6)) -> 0 | Q6: =IF($A6="","",P6/12) -> 0
A7: =IF(Configurações!A9="","",Configurações!A9) -> Outros ganhos | B7: =IF(Configurações!B9="","",Configurações!B9) -> Ganho | C7: =IF($A7="","",Configurações!C9) -> 0 | D7: =IF($A7="","",SUMIFS(Lançamentos!$D$5:$D$2004,Lançamentos!$B$5:$B$2004,$A7,Lançamentos!$H$5:$H$2004,D$4)) -> 0 | E7: =IF($A7="","",SUMIFS(Lançamentos!$D$5:$D$2004,Lançamentos!$B$5:$B$2004,$A7,Lançamentos!$H$5:$H$2004,E$4)) -> 0 | F7: =IF($A7="","",SUMIFS(Lançamentos!$D$5:$D$2004,Lançamentos!$B$5:$B$2004,$A7,Lançamentos!$H$5:$H$2004,F$4)) -> 0 | G7: =IF($A7="","",SUMIFS(Lançamentos!$D$5:$D$2004,Lançamentos!$B$5:$B$2004,$A7,Lançamentos!$H$5:$H$2004,G$4)) -> 0 | H7: =IF($A7="","",SUMIFS(Lançamentos!$D$5:$D$2004,Lançamentos!$B$5:$B$2004,$A7,Lançamentos!$H$5:$H$2004,H$4)) -> 0 | I7: =IF($A7="","",SUMIFS(Lançamentos!$D$5:$D$2004,Lançamentos!$B$5:$B$2004,$A7,Lançamentos!$H$5:$H$2004,I$4)) -> 0 | J7: =IF($A7="","",SUMIFS(Lançamentos!$D$5:$D$2004,Lançamentos!$B$5:$B$2004,$A7,Lançamentos!$H$5:$H$2004,J$4)) -> 0 | K7: =IF($A7="","",SUMIFS(Lançamentos!$D$5:$D$2004,Lançamentos!$B$5:$B$2004,$A7,Lançamentos!$H$5:$H$2004,K$4)) -> 0 | ... O7: =IF($A7="","",SUMIFS(Lançamentos!$D$5:$D$2004,Lançamentos!$B$5:$B$2004,$A7,Lançamentos!$H$5:$H$2004,O$4)) -> 0 | P7: =IF($A7="","",SUM(D7:O7)) -> 0 | Q7: =IF($A7="","",P7/12) -> 0
A8: =IF(Configurações!A10="","",Configurações!A10) -> Aluguel | B8: =IF(Configurações!B10="","",Configurações!B10) -> Gasto | C8: =IF($A8="","",Configurações!C10) -> 0 | D8: =IF($A8="","",SUMIFS(Lançamentos!$D$5:$D$2004,Lançamentos!$B$5:$B$2004,$A8,Lançamentos!$H$5:$H$2004,D$4)) -> 0 | E8: =IF($A8="","",SUMIFS(Lançamentos!$D$5:$D$2004,Lançamentos!$B$5:$B$2004,$A8,Lançamentos!$H$5:$H$2004,E$4)) -> 0 | F8: =IF($A8="","",SUMIFS(Lançamentos!$D$5:$D$2004,Lançamentos!$B$5:$B$2004,$A8,Lançamentos!$H$5:$H$2004,F$4)) -> 0 | G8: =IF($A8="","",SUMIFS(Lançamentos!$D$5:$D$2004,Lançamentos!$B$5:$B$2004,$A8,Lançamentos!$H$5:$H$2004,G$4)) -> 0 | H8: =IF($A8="","",SUMIFS(Lançamentos!$D$5:$D$2004,Lançamentos!$B$5:$B$2004,$A8,Lançamentos!$H$5:$H$2004,H$4)) -> 0 | I8: =IF($A8="","",SUMIFS(Lançamentos!$D$5:$D$2004,Lançamentos!$B$5:$B$2004,$A8,Lançamentos!$H$5:$H$2004,I$4)) -> 0 | J8: =IF($A8="","",SUMIFS(Lançamentos!$D$5:$D$2004,Lançamentos!$B$5:$B$2004,$A8,Lançamentos!$H$5:$H$2004,J$4)) -> 0 | K8: =IF($A8="","",SUMIFS(Lançamentos!$D$5:$D$2004,Lançamentos!$B$5:$B$2004,$A8,Lançamentos!$H$5:$H$2004,K$4)) -> 0 | ... O8: =IF($A8="","",SUMIFS(Lançamentos!$D$5:$D$2004,Lançamentos!$B$5:$B$2004,$A8,Lançamentos!$H$5:$H$2004,O$4)) -> 0 | P8: =IF($A8="","",SUM(D8:O8)) -> 0 | Q8: =IF($A8="","",P8/12) -> 0
A9: =IF(Configurações!A11="","",Configurações!A11) -> Luz | B9: =IF(Configurações!B11="","",Configurações!B11) -> Gasto | C9: =IF($A9="","",Configurações!C11) -> 0 | D9: =IF($A9="","",SUMIFS(Lançamentos!$D$5:$D$2004,Lançamentos!$B$5:$B$2004,$A9,Lançamentos!$H$5:$H$2004,D$4)) -> 0 | E9: =IF($A9="","",SUMIFS(Lançamentos!$D$5:$D$2004,Lançamentos!$B$5:$B$2004,$A9,Lançamentos!$H$5:$H$2004,E$4)) -> 0 | F9: =IF($A9="","",SUMIFS(Lançamentos!$D$5:$D$2004,Lançamentos!$B$5:$B$2004,$A9,Lançamentos!$H$5:$H$2004,F$4)) -> 0 | G9: =IF($A9="","",SUMIFS(Lançamentos!$D$5:$D$2004,Lançamentos!$B$5:$B$2004,$A9,Lançamentos!$H$5:$H$2004,G$4)) -> 0 | H9: =IF($A9="","",SUMIFS(Lançamentos!$D$5:$D$2004,Lançamentos!$B$5:$B$2004,$A9,Lançamentos!$H$5:$H$2004,H$4)) -> 0 | I9: =IF($A9="","",SUMIFS(Lançamentos!$D$5:$D$2004,Lançamentos!$B$5:$B$2004,$A9,Lançamentos!$H$5:$H$2004,I$4)) -> 0 | J9: =IF($A9="","",SUMIFS(Lançamentos!$D$5:$D$2004,Lançamentos!$B$5:$B$2004,$A9,Lançamentos!$H$5:$H$2004,J$4)) -> 0 | K9: =IF($A9="","",SUMIFS(Lançamentos!$D$5:$D$2004,Lançamentos!$B$5:$B$2004,$A9,Lançamentos!$H$5:$H$2004,K$4)) -> 0 | ... O9: =IF($A9="","",SUMIFS(Lançamentos!$D$5:$D$2004,Lançamentos!$B$5:$B$2004,$A9,Lançamentos!$H$5:$H$2004,O$4)) -> 0 | P9: =IF($A9="","",SUM(D9:O9)) -> 0 | Q9: =IF($A9="","",P9/12) -> 0
A10: =IF(Configurações!A12="","",Configurações!A12) -> Água | B10: =IF(Configurações!B12="","",Configurações!B12) -> Gasto | C10: =IF($A10="","",Configurações!C12) -> 0 | D10: =IF($A10="","",SUMIFS(Lançamentos!$D$5:$D$2004,Lançamentos!$B$5:$B$2004,$A10,Lançamentos!$H$5:$H$2004,D$4)) -> 0 | E10: =IF($A10="","",SUMIFS(Lançamentos!$D$5:$D$2004,Lançamentos!$B$5:$B$2004,$A10,Lançamentos!$H$5:$H$2004,E$4)) -> 0 | F10: =IF($A10="","",SUMIFS(Lançamentos!$D$5:$D$2004,Lançamentos!$B$5:$B$2004,$A10,Lançamentos!$H$5:$H$2004,F$4)) -> 0 | G10: =IF($A10="","",SUMIFS(Lançamentos!$D$5:$D$2004,Lançamentos!$B$5:$B$2004,$A10,Lançamentos!$H$5:$H$2004,G$4)) -> 0 | H10: =IF($A10="","",SUMIFS(Lançamentos!$D$5:$D$2004,Lançamentos!$B$5:$B$2004,$A10,Lançamentos!$H$5:$H$2004,H$4)) -> 0 | I10: =IF($A10="","",SUMIFS(Lançamentos!$D$5:$D$2004,Lançamentos!$B$5:$B$2004,$A10,Lançamentos!$H$5:$H$2004,I$4)) -> 0 | J10: =IF($A10="","",SUMIFS(Lançamentos!$D$5:$D$2004,Lançamentos!$B$5:$B$2004,$A10,Lançamentos!$H$5:$H$2004,J$4)) -> 0 | K10: =IF($A10="","",SUMIFS(Lançamentos!$D$5:$D$2004,Lançamentos!$B$5:$B$2004,$A10,Lançamentos!$H$5:$H$2004,K$4)) -> 0 | ... O10: =IF($A10="","",SUMIFS(Lançamentos!$D$5:$D$2004,Lançamentos!$B$5:$B$2004,$A10,Lançamentos!$H$5:$H$2004,O$4)) -> 0 | P10: =IF($A10="","",SUM(D10:O10)) -> 0 | Q10: =IF($A10="","",P10/12) -> 0
A11: =IF(Configurações!A13="","",Configurações!A13) -> Compras de casa | B11: =IF(Configurações!B13="","",Configurações!B13) -> Gasto | C11: =IF($A11="","",Configurações!C13) -> 0 | D11: =IF($A11="","",SUMIFS(Lançamentos!$D$5:$D$2004,Lançamentos!$B$5:$B$2004,$A11,Lançamentos!$H$5:$H$2004,D$4)) -> 0 | E11: =IF($A11="","",SUMIFS(Lançamentos!$D$5:$D$2004,Lançamentos!$B$5:$B$2004,$A11,Lançamentos!$H$5:$H$2004,E$4)) -> 0 | F11: =IF($A11="","",SUMIFS(Lançamentos!$D$5:$D$2004,Lançamentos!$B$5:$B$2004,$A11,Lançamentos!$H$5:$H$2004,F$4)) -> 0 | G11: =IF($A11="","",SUMIFS(Lançamentos!$D$5:$D$2004,Lançamentos!$B$5:$B$2004,$A11,Lançamentos!$H$5:$H$2004,G$4)) -> 0 | H11: =IF($A11="","",SUMIFS(Lançamentos!$D$5:$D$2004,Lançamentos!$B$5:$B$2004,$A11,Lançamentos!$H$5:$H$2004,H$4)) -> 0 | I11: =IF($A11="","",SUMIFS(Lançamentos!$D$5:$D$2004,Lançamentos!$B$5:$B$2004,$A11,Lançamentos!$H$5:$H$2004,I$4)) -> 0 | J11: =IF($A11="","",SUMIFS(Lançamentos!$D$5:$D$2004,Lançamentos!$B$5:$B$2004,$A11,Lançamentos!$H$5:$H$2004,J$4)) -> 0 | K11: =IF($A11="","",SUMIFS(Lançamentos!$D$5:$D$2004,Lançamentos!$B$5:$B$2004,$A11,Lançamentos!$H$5:$H$2004,K$4)) -> 0 | ... O11: =IF($A11="","",SUMIFS(Lançamentos!$D$5:$D$2004,Lançamentos!$B$5:$B$2004,$A11,Lançamentos!$H$5:$H$2004,O$4)) -> 0 | P11: =IF($A11="","",SUM(D11:O11)) -> 0 | Q11: =IF($A11="","",P11/12) -> 0
A12: =IF(Configurações!A14="","",Configurações!A14) -> Alimentação na rua | B12: =IF(Configurações!B14="","",Configurações!B14) -> Gasto | C12: =IF($A12="","",Configurações!C14) -> 0 | D12: =IF($A12="","",SUMIFS(Lançamentos!$D$5:$D$2004,Lançamentos!$B$5:$B$2004,$A12,Lançamentos!$H$5:$H$2004,D$4)) -> 0 | E12: =IF($A12="","",SUMIFS(Lançamentos!$D$5:$D$2004,Lançamentos!$B$5:$B$2004,$A12,Lançamentos!$H$5:$H$2004,E$4)) -> 0 | F12: =IF($A12="","",SUMIFS(Lançamentos!$D$5:$D$2004,Lançamentos!$B$5:$B$2004,$A12,Lançamentos!$H$5:$H$2004,F$4)) -> 0 | G12: =IF($A12="","",SUMIFS(Lançamentos!$D$5:$D$2004,Lançamentos!$B$5:$B$2004,$A12,Lançamentos!$H$5:$H$2004,G$4)) -> 0 | H12: =IF($A12="","",SUMIFS(Lançamentos!$D$5:$D$2004,Lançamentos!$B$5:$B$2004,$A12,Lançamentos!$H$5:$H$2004,H$4)) -> 0 | I12: =IF($A12="","",SUMIFS(Lançamentos!$D$5:$D$2004,Lançamentos!$B$5:$B$2004,$A12,Lançamentos!$H$5:$H$2004,I$4)) -> 0 | J12: =IF($A12="","",SUMIFS(Lançamentos!$D$5:$D$2004,Lançamentos!$B$5:$B$2004,$A12,Lançamentos!$H$5:$H$2004,J$4)) -> 0 | K12: =IF($A12="","",SUMIFS(Lançamentos!$D$5:$D$2004,Lançamentos!$B$5:$B$2004,$A12,Lançamentos!$H$5:$H$2004,K$4)) -> 0 | ... O12: =IF($A12="","",SUMIFS(Lançamentos!$D$5:$D$2004,Lançamentos!$B$5:$B$2004,$A12,Lançamentos!$H$5:$H$2004,O$4)) -> 0 | P12: =IF($A12="","",SUM(D12:O12)) -> 0 | Q12: =IF($A12="","",P12/12) -> 0
A13: =IF(Configurações!A15="","",Configurações!A15) -> iFood | B13: =IF(Configurações!B15="","",Configurações!B15) -> Gasto | C13: =IF($A13="","",Configurações!C15) -> 0 | D13: =IF($A13="","",SUMIFS(Lançamentos!$D$5:$D$2004,Lançamentos!$B$5:$B$2004,$A13,Lançamentos!$H$5:$H$2004,D$4)) -> 62.9 | E13: =IF($A13="","",SUMIFS(Lançamentos!$D$5:$D$2004,Lançamentos!$B$5:$B$2004,$A13,Lançamentos!$H$5:$H$2004,E$4)) -> 0 | F13: =IF($A13="","",SUMIFS(Lançamentos!$D$5:$D$2004,Lançamentos!$B$5:$B$2004,$A13,Lançamentos!$H$5:$H$2004,F$4)) -> 0 | G13: =IF($A13="","",SUMIFS(Lançamentos!$D$5:$D$2004,Lançamentos!$B$5:$B$2004,$A13,Lançamentos!$H$5:$H$2004,G$4)) -> 0 | H13: =IF($A13="","",SUMIFS(Lançamentos!$D$5:$D$2004,Lançamentos!$B$5:$B$2004,$A13,Lançamentos!$H$5:$H$2004,H$4)) -> 0 | I13: =IF($A13="","",SUMIFS(Lançamentos!$D$5:$D$2004,Lançamentos!$B$5:$B$2004,$A13,Lançamentos!$H$5:$H$2004,I$4)) -> 0 | J13: =IF($A13="","",SUMIFS(Lançamentos!$D$5:$D$2004,Lançamentos!$B$5:$B$2004,$A13,Lançamentos!$H$5:$H$2004,J$4)) -> 0 | K13: =IF($A13="","",SUMIFS(Lançamentos!$D$5:$D$2004,Lançamentos!$B$5:$B$2004,$A13,Lançamentos!$H$5:$H$2004,K$4)) -> 0 | ... O13: =IF($A13="","",SUMIFS(Lançamentos!$D$5:$D$2004,Lançamentos!$B$5:$B$2004,$A13,Lançamentos!$H$5:$H$2004,O$4)) -> 0 | P13: =IF($A13="","",SUM(D13:O13)) -> 62.9 | Q13: =IF($A13="","",P13/12) -> 5.2416667
A14: =IF(Configurações!A16="","",Configurações!A16) -> Bar | B14: =IF(Configurações!B16="","",Configurações!B16) -> Gasto | C14: =IF($A14="","",Configurações!C16) -> 0 | D14: =IF($A14="","",SUMIFS(Lançamentos!$D$5:$D$2004,Lançamentos!$B$5:$B$2004,$A14,Lançamentos!$H$5:$H$2004,D$4)) -> 0 | E14: =IF($A14="","",SUMIFS(Lançamentos!$D$5:$D$2004,Lançamentos!$B$5:$B$2004,$A14,Lançamentos!$H$5:$H$2004,E$4)) -> 0 | F14: =IF($A14="","",SUMIFS(Lançamentos!$D$5:$D$2004,Lançamentos!$B$5:$B$2004,$A14,Lançamentos!$H$5:$H$2004,F$4)) -> 0 | G14: =IF($A14="","",SUMIFS(Lançamentos!$D$5:$D$2004,Lançamentos!$B$5:$B$2004,$A14,Lançamentos!$H$5:$H$2004,G$4)) -> 0 | H14: =IF($A14="","",SUMIFS(Lançamentos!$D$5:$D$2004,Lançamentos!$B$5:$B$2004,$A14,Lançamentos!$H$5:$H$2004,H$4)) -> 0 | I14: =IF($A14="","",SUMIFS(Lançamentos!$D$5:$D$2004,Lançamentos!$B$5:$B$2004,$A14,Lançamentos!$H$5:$H$2004,I$4)) -> 0 | J14: =IF($A14="","",SUMIFS(Lançamentos!$D$5:$D$2004,Lançamentos!$B$5:$B$2004,$A14,Lançamentos!$H$5:$H$2004,J$4)) -> 0 | K14: =IF($A14="","",SUMIFS(Lançamentos!$D$5:$D$2004,Lançamentos!$B$5:$B$2004,$A14,Lançamentos!$H$5:$H$2004,K$4)) -> 0 | ... O14: =IF($A14="","",SUMIFS(Lançamentos!$D$5:$D$2004,Lançamentos!$B$5:$B$2004,$A14,Lançamentos!$H$5:$H$2004,O$4)) -> 0 | P14: =IF($A14="","",SUM(D14:O14)) -> 0 | Q14: =IF($A14="","",P14/12) -> 0
A15: =IF(Configurações!A17="","",Configurações!A17) -> Transporte | B15: =IF(Configurações!B17="","",Configurações!B17) -> Gasto | C15: =IF($A15="","",Configurações!C17) -> 0 | D15: =IF($A15="","",SUMIFS(Lançamentos!$D$5:$D$2004,Lançamentos!$B$5:$B$2004,$A15,Lançamentos!$H$5:$H$2004,D$4)) -> 0 | E15: =IF($A15="","",SUMIFS(Lançamentos!$D$5:$D$2004,Lançamentos!$B$5:$B$2004,$A15,Lançamentos!$H$5:$H$2004,E$4)) -> 0 | F15: =IF($A15="","",SUMIFS(Lançamentos!$D$5:$D$2004,Lançamentos!$B$5:$B$2004,$A15,Lançamentos!$H$5:$H$2004,F$4)) -> 0 | G15: =IF($A15="","",SUMIFS(Lançamentos!$D$5:$D$2004,Lançamentos!$B$5:$B$2004,$A15,Lançamentos!$H$5:$H$2004,G$4)) -> 0 | H15: =IF($A15="","",SUMIFS(Lançamentos!$D$5:$D$2004,Lançamentos!$B$5:$B$2004,$A15,Lançamentos!$H$5:$H$2004,H$4)) -> 0 | I15: =IF($A15="","",SUMIFS(Lançamentos!$D$5:$D$2004,Lançamentos!$B$5:$B$2004,$A15,Lançamentos!$H$5:$H$2004,I$4)) -> 0 | J15: =IF($A15="","",SUMIFS(Lançamentos!$D$5:$D$2004,Lançamentos!$B$5:$B$2004,$A15,Lançamentos!$H$5:$H$2004,J$4)) -> 0 | K15: =IF($A15="","",SUMIFS(Lançamentos!$D$5:$D$2004,Lançamentos!$B$5:$B$2004,$A15,Lançamentos!$H$5:$H$2004,K$4)) -> 0 | ... O15: =IF($A15="","",SUMIFS(Lançamentos!$D$5:$D$2004,Lançamentos!$B$5:$B$2004,$A15,Lançamentos!$H$5:$H$2004,O$4)) -> 0 | P15: =IF($A15="","",SUM(D15:O15)) -> 0 | Q15: =IF($A15="","",P15/12) -> 0
A16: =IF(Configurações!A18="","",Configurações!A18) -> Internet/Celular | B16: =IF(Configurações!B18="","",Configurações!B18) -> Gasto | C16: =IF($A16="","",Configurações!C18) -> 0 | D16: =IF($A16="","",SUMIFS(Lançamentos!$D$5:$D$2004,Lançamentos!$B$5:$B$2004,$A16,Lançamentos!$H$5:$H$2004,D$4)) -> 0 | E16: =IF($A16="","",SUMIFS(Lançamentos!$D$5:$D$2004,Lançamentos!$B$5:$B$2004,$A16,Lançamentos!$H$5:$H$2004,E$4)) -> 0 | F16: =IF($A16="","",SUMIFS(Lançamentos!$D$5:$D$2004,Lançamentos!$B$5:$B$2004,$A16,Lançamentos!$H$5:$H$2004,F$4)) -> 0 | G16: =IF($A16="","",SUMIFS(Lançamentos!$D$5:$D$2004,Lançamentos!$B$5:$B$2004,$A16,Lançamentos!$H$5:$H$2004,G$4)) -> 0 | H16: =IF($A16="","",SUMIFS(Lançamentos!$D$5:$D$2004,Lançamentos!$B$5:$B$2004,$A16,Lançamentos!$H$5:$H$2004,H$4)) -> 0 | I16: =IF($A16="","",SUMIFS(Lançamentos!$D$5:$D$2004,Lançamentos!$B$5:$B$2004,$A16,Lançamentos!$H$5:$H$2004,I$4)) -> 0 | J16: =IF($A16="","",SUMIFS(Lançamentos!$D$5:$D$2004,Lançamentos!$B$5:$B$2004,$A16,Lançamentos!$H$5:$H$2004,J$4)) -> 0 | K16: =IF($A16="","",SUMIFS(Lançamentos!$D$5:$D$2004,Lançamentos!$B$5:$B$2004,$A16,Lançamentos!$H$5:$H$2004,K$4)) -> 0 | ... O16: =IF($A16="","",SUMIFS(Lançamentos!$D$5:$D$2004,Lançamentos!$B$5:$B$2004,$A16,Lançamentos!$H$5:$H$2004,O$4)) -> 0 | P16: =IF($A16="","",SUM(D16:O16)) -> 0 | Q16: =IF($A16="","",P16/12) -> 0
... A28: =IF(Configurações!A30="","",Configurações!A30) | B28: =IF(Configurações!B30="","",Configurações!B30) | C28: =IF($A28="","",Configurações!C30) | D28: =IF($A28="","",SUMIFS(Lançamentos!$D$5:$D$2004,Lançamentos!$B$5:$B$2004,$A28,Lançamentos!$H$5:$H$2004,D$4)) | E28: =IF($A28="","",SUMIFS(Lançamentos!$D$5:$D$2004,Lançamentos!$B$5:$B$2004,$A28,Lançamentos!$H$5:$H$2004,E$4)) | F28: =IF($A28="","",SUMIFS(Lançamentos!$D$5:$D$2004,Lançamentos!$B$5:$B$2004,$A28,Lançamentos!$H$5:$H$2004,F$4)) | G28: =IF($A28="","",SUMIFS(Lançamentos!$D$5:$D$2004,Lançamentos!$B$5:$B$2004,$A28,Lançamentos!$H$5:$H$2004,G$4)) | H28: =IF($A28="","",SUMIFS(Lançamentos!$D$5:$D$2004,Lançamentos!$B$5:$B$2004,$A28,Lançamentos!$H$5:$H$2004,H$4)) | I28: =IF($A28="","",SUMIFS(Lançamentos!$D$5:$D$2004,Lançamentos!$B$5:$B$2004,$A28,Lançamentos!$H$5:$H$2004,I$4)) | J28: =IF($A28="","",SUMIFS(Lançamentos!$D$5:$D$2004,Lançamentos!$B$5:$B$2004,$A28,Lançamentos!$H$5:$H$2004,J$4)) | K28: =IF($A28="","",SUMIFS(Lançamentos!$D$5:$D$2004,Lançamentos!$B$5:$B$2004,$A28,Lançamentos!$H$5:$H$2004,K$4)) | ... O28: =IF($A28="","",SUMIFS(Lançamentos!$D$5:$D$2004,Lançamentos!$B$5:$B$2004,$A28,Lançamentos!$H$5:$H$2004,O$4)) | P28: =IF($A28="","",SUM(D28:O28)) | Q28: =IF($A28="","",P28/12)
A30: Total ganhos | C30: =SUMIFS(C$5:C$28,$B$5:$B$28,"Ganho") -> 0 | D30: =SUMIFS(D$5:D$28,$B$5:$B$28,"Ganho") -> 0 | E30: =SUMIFS(E$5:E$28,$B$5:$B$28,"Ganho") -> 0 | F30: =SUMIFS(F$5:F$28,$B$5:$B$28,"Ganho") -> 0 | G30: =SUMIFS(G$5:G$28,$B$5:$B$28,"Ganho") -> 0 | H30: =SUMIFS(H$5:H$28,$B$5:$B$28,"Ganho") -> 0 | I30: =SUMIFS(I$5:I$28,$B$5:$B$28,"Ganho") -> 0 | J30: =SUMIFS(J$5:J$28,$B$5:$B$28,"Ganho") -> 0 | ... Q30: =SUMIFS(Q$5:Q$28,$B$5:$B$28,"Ganho") -> 0
A31: Total gastos | C31: =SUMIFS(C$5:C$28,$B$5:$B$28,"Gasto") -> 0 | D31: =SUMIFS(D$5:D$28,$B$5:$B$28,"Gasto") -> 62.9 | E31: =SUMIFS(E$5:E$28,$B$5:$B$28,"Gasto") -> 0 | F31: =SUMIFS(F$5:F$28,$B$5:$B$28,"Gasto") -> 0 | G31: =SUMIFS(G$5:G$28,$B$5:$B$28,"Gasto") -> 0 | H31: =SUMIFS(H$5:H$28,$B$5:$B$28,"Gasto") -> 0 | I31: =SUMIFS(I$5:I$28,$B$5:$B$28,"Gasto") -> 0 | J31: =SUMIFS(J$5:J$28,$B$5:$B$28,"Gasto") -> 0 | ... Q31: =SUMIFS(Q$5:Q$28,$B$5:$B$28,"Gasto") -> 5.2416667
A32: Saldo do mês (sobrou) | C32: =C30-C31 -> 0 | D32: =D30-D31 -> -62.9 | E32: =E30-E31 -> 0 | F32: =F30-F31 -> 0 | G32: =G30-G31 -> 0 | H32: =H30-H31 -> 0 | I32: =I30-I31 -> 0 | J32: =J30-J31 -> 0 | ... Q32: =Q30-Q31 -> -5.2416667
A33: Saldo acumulado | D33: =D32 -> -62.9 | E33: =D33+E32 -> -62.9 | F33: =E33+F32 -> -62.9 | G33: =F33+G32 -> -62.9 | H33: =G33+H32 -> -62.9 | I33: =H33+I32 -> -62.9 | J33: =I33+J32 -> -62.9 | K33: =J33+K32 -> -62.9 | L33: =K33+L32 -> -62.9 | ... O33: =N33+O32 -> -62.9
A34: Diferença vs. previsto | D34: =D32-$C$32 -> -62.9 | E34: =E32-$C$32 -> 0 | F34: =F32-$C$32 -> 0 | G34: =G32-$C$32 -> 0 | H34: =H32-$C$32 -> 0 | I34: =I32-$C$32 -> 0 | J34: =J32-$C$32 -> 0 | K34: =K32-$C$32 -> 0 | ... O34: =O32-$C$32 -> 0

Sheet Resumo Semanal
A1: Resumo semanal
A2: Semanas de segunda a domingo. Bom pra fechar a semana e ver onde o dinheiro foi.
A4: Semana (seg.) | B4: até (dom.) | C4: Ganhos | D4: Gastos | E4: Saldo | F4: =Configurações!A10 -> Aluguel | G4: =Configurações!A11 -> Luz | H4: =Configurações!A12 -> Água | I4: =Configurações!A13 -> Compras de casa | J4: =Configurações!A14 -> Alimentação na rua | K4: =Configurações!A15 -> iFood | L4: =Configurações!A16 -> Bar | M4: =Configurações!A17 -> Transporte | N4: =Configurações!A18 -> Internet/Celular | O4: =Configurações!A19 -> Assinaturas | P4: =Configurações!A20 -> Saúde | Q4: =Configurações!A21 -> Lazer | R4: =Configurações!A22 -> Outros gastos
A5: =Configurações!$B$4-WEEKDAY(Configurações!$B$4,2)+1 -> 46293 | B5: =A5+6 -> 46299 | C5: =SUMIFS(Lançamentos!$D$5:$D$2004,Lançamentos!$F$5:$F$2004,"Ganho",Lançamentos!$G$5:$G$2004,$A5) -> 0 | D5: =SUMIFS(Lançamentos!$D$5:$D$2004,Lançamentos!$F$5:$F$2004,"Gasto",Lançamentos!$G$5:$G$2004,$A5) -> 0 | E5: =C5-D5 -> 0 | F5: =SUMIFS(Lançamentos!$D$5:$D$2004,Lançamentos!$B$5:$B$2004,F$4,Lançamentos!$G$5:$G$2004,$A5) -> 0 | G5: =SUMIFS(Lançamentos!$D$5:$D$2004,Lançamentos!$B$5:$B$2004,G$4,Lançamentos!$G$5:$G$2004,$A5) -> 0 | H5: =SUMIFS(Lançamentos!$D$5:$D$2004,Lançamentos!$B$5:$B$2004,H$4,Lançamentos!$G$5:$G$2004,$A5) -> 0 | I5: =SUMIFS(Lançamentos!$D$5:$D$2004,Lançamentos!$B$5:$B$2004,I$4,Lançamentos!$G$5:$G$2004,$A5) -> 0 | J5: =SUMIFS(Lançamentos!$D$5:$D$2004,Lançamentos!$B$5:$B$2004,J$4,Lançamentos!$G$5:$G$2004,$A5) -> 0 | K5: =SUMIFS(Lançamentos!$D$5:$D$2004,Lançamentos!$B$5:$B$2004,K$4,Lançamentos!$G$5:$G$2004,$A5) -> 0 | L5: =SUMIFS(Lançamentos!$D$5:$D$2004,Lançamentos!$B$5:$B$2004,L$4,Lançamentos!$G$5:$G$2004,$A5) -> 0 | M5: =SUMIFS(Lançamentos!$D$5:$D$2004,Lançamentos!$B$5:$B$2004,M$4,Lançamentos!$G$5:$G$2004,$A5) -> 0 | ... R5: =SUMIFS(Lançamentos!$D$5:$D$2004,Lançamentos!$B$5:$B$2004,R$4,Lançamentos!$G$5:$G$2004,$A5) -> 0
A6: =A5+7 -> 46300 | B6: =A6+6 -> 46306 | C6: =SUMIFS(Lançamentos!$D$5:$D$2004,Lançamentos!$F$5:$F$2004,"Ganho",Lançamentos!$G$5:$G$2004,$A6) -> 0 | D6: =SUMIFS(Lançamentos!$D$5:$D$2004,Lançamentos!$F$5:$F$2004,"Gasto",Lançamentos!$G$5:$G$2004,$A6) -> 62.9 | E6: =C6-D6 -> -62.9 | F6: =SUMIFS(Lançamentos!$D$5:$D$2004,Lançamentos!$B$5:$B$2004,F$4,Lançamentos!$G$5:$G$2004,$A6) -> 0 | G6: =SUMIFS(Lançamentos!$D$5:$D$2004,Lançamentos!$B$5:$B$2004,G$4,Lançamentos!$G$5:$G$2004,$A6) -> 0 | H6: =SUMIFS(Lançamentos!$D$5:$D$2004,Lançamentos!$B$5:$B$2004,H$4,Lançamentos!$G$5:$G$2004,$A6) -> 0 | I6: =SUMIFS(Lançamentos!$D$5:$D$2004,Lançamentos!$B$5:$B$2004,I$4,Lançamentos!$G$5:$G$2004,$A6) -> 0 | J6: =SUMIFS(Lançamentos!$D$5:$D$2004,Lançamentos!$B$5:$B$2004,J$4,Lançamentos!$G$5:$G$2004,$A6) -> 0 | K6: =SUMIFS(Lançamentos!$D$5:$D$2004,Lançamentos!$B$5:$B$2004,K$4,Lançamentos!$G$5:$G$2004,$A6) -> 62.9 | L6: =SUMIFS(Lançamentos!$D$5:$D$2004,Lançamentos!$B$5:$B$2004,L$4,Lançamentos!$G$5:$G$2004,$A6) -> 0 | M6: =SUMIFS(Lançamentos!$D$5:$D$2004,Lançamentos!$B$5:$B$2004,M$4,Lançamentos!$G$5:$G$2004,$A6) -> 0 | ... R6: =SUMIFS(Lançamentos!$D$5:$D$2004,Lançamentos!$B$5:$B$2004,R$4,Lançamentos!$G$5:$G$2004,$A6) -> 0
A7: =A6+7 -> 46307 | B7: =A7+6 -> 46313 | C7: =SUMIFS(Lançamentos!$D$5:$D$2004,Lançamentos!$F$5:$F$2004,"Ganho",Lançamentos!$G$5:$G$2004,$A7) -> 0 | D7: =SUMIFS(Lançamentos!$D$5:$D$2004,Lançamentos!$F$5:$F$2004,"Gasto",Lançamentos!$G$5:$G$2004,$A7) -> 0 | E7: =C7-D7 -> 0 | F7: =SUMIFS(Lançamentos!$D$5:$D$2004,Lançamentos!$B$5:$B$2004,F$4,Lançamentos!$G$5:$G$2004,$A7) -> 0 | G7: =SUMIFS(Lançamentos!$D$5:$D$2004,Lançamentos!$B$5:$B$2004,G$4,Lançamentos!$G$5:$G$2004,$A7) -> 0 | H7: =SUMIFS(Lançamentos!$D$5:$D$2004,Lançamentos!$B$5:$B$2004,H$4,Lançamentos!$G$5:$G$2004,$A7) -> 0 | I7: =SUMIFS(Lançamentos!$D$5:$D$2004,Lançamentos!$B$5:$B$2004,I$4,Lançamentos!$G$5:$G$2004,$A7) -> 0 | J7: =SUMIFS(Lançamentos!$D$5:$D$2004,Lançamentos!$B$5:$B$2004,J$4,Lançamentos!$G$5:$G$2004,$A7) -> 0 | K7: =SUMIFS(Lançamentos!$D$5:$D$2004,Lançamentos!$B$5:$B$2004,K$4,Lançamentos!$G$5:$G$2004,$A7) -> 0 | L7: =SUMIFS(Lançamentos!$D$5:$D$2004,Lançamentos!$B$5:$B$2004,L$4,Lançamentos!$G$5:$G$2004,$A7) -> 0 | M7: =SUMIFS(Lançamentos!$D$5:$D$2004,Lançamentos!$B$5:$B$2004,M$4,Lançamentos!$G$5:$G$2004,$A7) -> 0 | ... R7: =SUMIFS(Lançamentos!$D$5:$D$2004,Lançamentos!$B$5:$B$2004,R$4,Lançamentos!$G$5:$G$2004,$A7) -> 0
A8: =A7+7 -> 46314 | B8: =A8+6 -> 46320 | C8: =SUMIFS(Lançamentos!$D$5:$D$2004,Lançamentos!$F$5:$F$2004,"Ganho",Lançamentos!$G$5:$G$2004,$A8) -> 0 | D8: =SUMIFS(Lançamentos!$D$5:$D$2004,Lançamentos!$F$5:$F$2004,"Gasto",Lançamentos!$G$5:$G$2004,$A8) -> 0 | E8: =C8-D8 -> 0 | F8: =SUMIFS(Lançamentos!$D$5:$D$2004,Lançamentos!$B$5:$B$2004,F$4,Lançamentos!$G$5:$G$2004,$A8) -> 0 | G8: =SUMIFS(Lançamentos!$D$5:$D$2004,Lançamentos!$B$5:$B$2004,G$4,Lançamentos!$G$5:$G$2004,$A8) -> 0 | H8: =SUMIFS(Lançamentos!$D$5:$D$2004,Lançamentos!$B$5:$B$2004,H$4,Lançamentos!$G$5:$G$2004,$A8) -> 0 | I8: =SUMIFS(Lançamentos!$D$5:$D$2004,Lançamentos!$B$5:$B$2004,I$4,Lançamentos!$G$5:$G$2004,$A8) -> 0 | J8: =SUMIFS(Lançamentos!$D$5:$D$2004,Lançamentos!$B$5:$B$2004,J$4,Lançamentos!$G$5:$G$2004,$A8) -> 0 | K8: =SUMIFS(Lançamentos!$D$5:$D$2004,Lançamentos!$B$5:$B$2004,K$4,Lançamentos!$G$5:$G$2004,$A8) -> 0 | L8: =SUMIFS(Lançamentos!$D$5:$D$2004,Lançamentos!$B$5:$B$2004,L$4,Lançamentos!$G$5:$G$2004,$A8) -> 0 | M8: =SUMIFS(Lançamentos!$D$5:$D$2004,Lançamentos!$B$5:$B$2004,M$4,Lançamentos!$G$5:$G$2004,$A8) -> 0 | ... R8: =SUMIFS(Lançamentos!$D$5:$D$2004,Lançamentos!$B$5:$B$2004,R$4,Lançamentos!$G$5:$G$2004,$A8) -> 0
A9: =A8+7 -> 46321 | B9: =A9+6 -> 46327 | C9: =SUMIFS(Lançamentos!$D$5:$D$2004,Lançamentos!$F$5:$F$2004,"Ganho",Lançamentos!$G$5:$G$2004,$A9) -> 0 | D9: =SUMIFS(Lançamentos!$D$5:$D$2004,Lançamentos!$F$5:$F$2004,"Gasto",Lançamentos!$G$5:$G$2004,$A9) -> 0 | E9: =C9-D9 -> 0 | F9: =SUMIFS(Lançamentos!$D$5:$D$2004,Lançamentos!$B$5:$B$2004,F$4,Lançamentos!$G$5:$G$2004,$A9) -> 0 | G9: =SUMIFS(Lançamentos!$D$5:$D$2004,Lançamentos!$B$5:$B$2004,G$4,Lançamentos!$G$5:$G$2004,$A9) -> 0 | H9: =SUMIFS(Lançamentos!$D$5:$D$2004,Lançamentos!$B$5:$B$2004,H$4,Lançamentos!$G$5:$G$2004,$A9) -> 0 | I9: =SUMIFS(Lançamentos!$D$5:$D$2004,Lançamentos!$B$5:$B$2004,I$4,Lançamentos!$G$5:$G$2004,$A9) -> 0 | J9: =SUMIFS(Lançamentos!$D$5:$D$2004,Lançamentos!$B$5:$B$2004,J$4,Lançamentos!$G$5:$G$2004,$A9) -> 0 | K9: =SUMIFS(Lançamentos!$D$5:$D$2004,Lançamentos!$B$5:$B$2004,K$4,Lançamentos!$G$5:$G$2004,$A9) -> 0 | L9: =SUMIFS(Lançamentos!$D$5:$D$2004,Lançamentos!$B$5:$B$2004,L$4,Lançamentos!$G$5:$G$2004,$A9) -> 0 | M9: =SUMIFS(Lançamentos!$D$5:$D$2004,Lançamentos!$B$5:$B$2004,M$4,Lançamentos!$G$5:$G$2004,$A9) -> 0 | ... R9: =SUMIFS(Lançamentos!$D$5:$D$2004,Lançamentos!$B$5:$B$2004,R$4,Lançamentos!$G$5:$G$2004,$A9) -> 0
A10: =A9+7 -> 46328 | B10: =A10+6 -> 46334 | C10: =SUMIFS(Lançamentos!$D$5:$D$2004,Lançamentos!$F$5:$F$2004,"Ganho",Lançamentos!$G$5:$G$2004,$A10) -> 0 | D10: =SUMIFS(Lançamentos!$D$5:$D$2004,Lançamentos!$F$5:$F$2004,"Gasto",Lançamentos!$G$5:$G$2004,$A10) -> 0 | E10: =C10-D10 -> 0 | F10: =SUMIFS(Lançamentos!$D$5:$D$2004,Lançamentos!$B$5:$B$2004,F$4,Lançamentos!$G$5:$G$2004,$A10) -> 0 | G10: =SUMIFS(Lançamentos!$D$5:$D$2004,Lançamentos!$B$5:$B$2004,G$4,Lançamentos!$G$5:$G$2004,$A10) -> 0 | H10: =SUMIFS(Lançamentos!$D$5:$D$2004,Lançamentos!$B$5:$B$2004,H$4,Lançamentos!$G$5:$G$2004,$A10) -> 0 | I10: =SUMIFS(Lançamentos!$D$5:$D$2004,Lançamentos!$B$5:$B$2004,I$4,Lançamentos!$G$5:$G$2004,$A10) -> 0 | J10: =SUMIFS(Lançamentos!$D$5:$D$2004,Lançamentos!$B$5:$B$2004,J$4,Lançamentos!$G$5:$G$2004,$A10) -> 0 | K10: =SUMIFS(Lançamentos!$D$5:$D$2004,Lançamentos!$B$5:$B$2004,K$4,Lançamentos!$G$5:$G$2004,$A10) -> 0 | L10: =SUMIFS(Lançamentos!$D$5:$D$2004,Lançamentos!$B$5:$B$2004,L$4,Lançamentos!$G$5:$G$2004,$A10) -> 0 | M10: =SUMIFS(Lançamentos!$D$5:$D$2004,Lançamentos!$B$5:$B$2004,M$4,Lançamentos!$G$5:$G$2004,$A10) -> 0 | ... R10: =SUMIFS(Lançamentos!$D$5:$D$2004,Lançamentos!$B$5:$B$2004,R$4,Lançamentos!$G$5:$G$2004,$A10) -> 0
A11: =A10+7 -> 46335 | B11: =A11+6 -> 46341 | C11: =SUMIFS(Lançamentos!$D$5:$D$2004,Lançamentos!$F$5:$F$2004,"Ganho",Lançamentos!$G$5:$G$2004,$A11) -> 0 | D11: =SUMIFS(Lançamentos!$D$5:$D$2004,Lançamentos!$F$5:$F$2004,"Gasto",Lançamentos!$G$5:$G$2004,$A11) -> 0 | E11: =C11-D11 -> 0 | F11: =SUMIFS(Lançamentos!$D$5:$D$2004,Lançamentos!$B$5:$B$2004,F$4,Lançamentos!$G$5:$G$2004,$A11) -> 0 | G11: =SUMIFS(Lançamentos!$D$5:$D$2004,Lançamentos!$B$5:$B$2004,G$4,Lançamentos!$G$5:$G$2004,$A11) -> 0 | H11: =SUMIFS(Lançamentos!$D$5:$D$2004,Lançamentos!$B$5:$B$2004,H$4,Lançamentos!$G$5:$G$2004,$A11) -> 0 | I11: =SUMIFS(Lançamentos!$D$5:$D$2004,Lançamentos!$B$5:$B$2004,I$4,Lançamentos!$G$5:$G$2004,$A11) -> 0 | J11: =SUMIFS(Lançamentos!$D$5:$D$2004,Lançamentos!$B$5:$B$2004,J$4,Lançamentos!$G$5:$G$2004,$A11) -> 0 | K11: =SUMIFS(Lançamentos!$D$5:$D$2004,Lançamentos!$B$5:$B$2004,K$4,Lançamentos!$G$5:$G$2004,$A11) -> 0 | L11: =SUMIFS(Lançamentos!$D$5:$D$2004,Lançamentos!$B$5:$B$2004,L$4,Lançamentos!$G$5:$G$2004,$A11) -> 0 | M11: =SUMIFS(Lançamentos!$D$5:$D$2004,Lançamentos!$B$5:$B$2004,M$4,Lançamentos!$G$5:$G$2004,$A11) -> 0 | ... R11: =SUMIFS(Lançamentos!$D$5:$D$2004,Lançamentos!$B$5:$B$2004,R$4,Lançamentos!$G$5:$G$2004,$A11) -> 0
A12: =A11+7 -> 46342 | B12: =A12+6 -> 46348 | C12: =SUMIFS(Lançamentos!$D$5:$D$2004,Lançamentos!$F$5:$F$2004,"Ganho",Lançamentos!$G$5:$G$2004,$A12) -> 0 | D12: =SUMIFS(Lançamentos!$D$5:$D$2004,Lançamentos!$F$5:$F$2004,"Gasto",Lançamentos!$G$5:$G$2004,$A12) -> 0 | E12: =C12-D12 -> 0 | F12: =SUMIFS(Lançamentos!$D$5:$D$2004,Lançamentos!$B$5:$B$2004,F$4,Lançamentos!$G$5:$G$2004,$A12) -> 0 | G12: =SUMIFS(Lançamentos!$D$5:$D$2004,Lançamentos!$B$5:$B$2004,G$4,Lançamentos!$G$5:$G$2004,$A12) -> 0 | H12: =SUMIFS(Lançamentos!$D$5:$D$2004,Lançamentos!$B$5:$B$2004,H$4,Lançamentos!$G$5:$G$2004,$A12) -> 0 | I12: =SUMIFS(Lançamentos!$D$5:$D$2004,Lançamentos!$B$5:$B$2004,I$4,Lançamentos!$G$5:$G$2004,$A12) -> 0 | J12: =SUMIFS(Lançamentos!$D$5:$D$2004,Lançamentos!$B$5:$B$2004,J$4,Lançamentos!$G$5:$G$2004,$A12) -> 0 | K12: =SUMIFS(Lançamentos!$D$5:$D$2004,Lançamentos!$B$5:$B$2004,K$4,Lançamentos!$G$5:$G$2004,$A12) -> 0 | L12: =SUMIFS(Lançamentos!$D$5:$D$2004,Lançamentos!$B$5:$B$2004,L$4,Lançamentos!$G$5:$G$2004,$A12) -> 0 | M12: =SUMIFS(Lançamentos!$D$5:$D$2004,Lançamentos!$B$5:$B$2004,M$4,Lançamentos!$G$5:$G$2004,$A12) -> 0 | ... R12: =SUMIFS(Lançamentos!$D$5:$D$2004,Lançamentos!$B$5:$B$2004,R$4,Lançamentos!$G$5:$G$2004,$A12) -> 0
A13: =A12+7 -> 46349 | B13: =A13+6 -> 46355 | C13: =SUMIFS(Lançamentos!$D$5:$D$2004,Lançamentos!$F$5:$F$2004,"Ganho",Lançamentos!$G$5:$G$2004,$A13) -> 0 | D13: =SUMIFS(Lançamentos!$D$5:$D$2004,Lançamentos!$F$5:$F$2004,"Gasto",Lançamentos!$G$5:$G$2004,$A13) -> 0 | E13: =C13-D13 -> 0 | F13: =SUMIFS(Lançamentos!$D$5:$D$2004,Lançamentos!$B$5:$B$2004,F$4,Lançamentos!$G$5:$G$2004,$A13) -> 0 | G13: =SUMIFS(Lançamentos!$D$5:$D$2004,Lançamentos!$B$5:$B$2004,G$4,Lançamentos!$G$5:$G$2004,$A13) -> 0 | H13: =SUMIFS(Lançamentos!$D$5:$D$2004,Lançamentos!$B$5:$B$2004,H$4,Lançamentos!$G$5:$G$2004,$A13) -> 0 | I13: =SUMIFS(Lançamentos!$D$5:$D$2004,Lançamentos!$B$5:$B$2004,I$4,Lançamentos!$G$5:$G$2004,$A13) -> 0 | J13: =SUMIFS(Lançamentos!$D$5:$D$2004,Lançamentos!$B$5:$B$2004,J$4,Lançamentos!$G$5:$G$2004,$A13) -> 0 | K13: =SUMIFS(Lançamentos!$D$5:$D$2004,Lançamentos!$B$5:$B$2004,K$4,Lançamentos!$G$5:$G$2004,$A13) -> 0 | L13: =SUMIFS(Lançamentos!$D$5:$D$2004,Lançamentos!$B$5:$B$2004,L$4,Lançamentos!$G$5:$G$2004,$A13) -> 0 | M13: =SUMIFS(Lançamentos!$D$5:$D$2004,Lançamentos!$B$5:$B$2004,M$4,Lançamentos!$G$5:$G$2004,$A13) -> 0 | ... R13: =SUMIFS(Lançamentos!$D$5:$D$2004,Lançamentos!$B$5:$B$2004,R$4,Lançamentos!$G$5:$G$2004,$A13) -> 0
A14: =A13+7 -> 46356 | B14: =A14+6 -> 46362 | C14: =SUMIFS(Lançamentos!$D$5:$D$2004,Lançamentos!$F$5:$F$2004,"Ganho",Lançamentos!$G$5:$G$2004,$A14) -> 0 | D14: =SUMIFS(Lançamentos!$D$5:$D$2004,Lançamentos!$F$5:$F$2004,"Gasto",Lançamentos!$G$5:$G$2004,$A14) -> 0 | E14: =C14-D14 -> 0 | F14: =SUMIFS(Lançamentos!$D$5:$D$2004,Lançamentos!$B$5:$B$2004,F$4,Lançamentos!$G$5:$G$2004,$A14) -> 0 | G14: =SUMIFS(Lançamentos!$D$5:$D$2004,Lançamentos!$B$5:$B$2004,G$4,Lançamentos!$G$5:$G$2004,$A14) -> 0 | H14: =SUMIFS(Lançamentos!$D$5:$D$2004,Lançamentos!$B$5:$B$2004,H$4,Lançamentos!$G$5:$G$2004,$A14) -> 0 | I14: =SUMIFS(Lançamentos!$D$5:$D$2004,Lançamentos!$B$5:$B$2004,I$4,Lançamentos!$G$5:$G$2004,$A14) -> 0 | J14: =SUMIFS(Lançamentos!$D$5:$D$2004,Lançamentos!$B$5:$B$2004,J$4,Lançamentos!$G$5:$G$2004,$A14) -> 0 | K14: =SUMIFS(Lançamentos!$D$5:$D$2004,Lançamentos!$B$5:$B$2004,K$4,Lançamentos!$G$5:$G$2004,$A14) -> 0 | L14: =SUMIFS(Lançamentos!$D$5:$D$2004,Lançamentos!$B$5:$B$2004,L$4,Lançamentos!$G$5:$G$2004,$A14) -> 0 | M14: =SUMIFS(Lançamentos!$D$5:$D$2004,Lançamentos!$B$5:$B$2004,M$4,Lançamentos!$G$5:$G$2004,$A14) -> 0 | ... R14: =SUMIFS(Lançamentos!$D$5:$D$2004,Lançamentos!$B$5:$B$2004,R$4,Lançamentos!$G$5:$G$2004,$A14) -> 0
A15: =A14+7 -> 46363 | B15: =A15+6 -> 46369 | C15: =SUMIFS(Lançamentos!$D$5:$D$2004,Lançamentos!$F$5:$F$2004,"Ganho",Lançamentos!$G$5:$G$2004,$A15) -> 0 | D15: =SUMIFS(Lançamentos!$D$5:$D$2004,Lançamentos!$F$5:$F$2004,"Gasto",Lançamentos!$G$5:$G$2004,$A15) -> 0 | E15: =C15-D15 -> 0 | F15: =SUMIFS(Lançamentos!$D$5:$D$2004,Lançamentos!$B$5:$B$2004,F$4,Lançamentos!$G$5:$G$2004,$A15) -> 0 | G15: =SUMIFS(Lançamentos!$D$5:$D$2004,Lançamentos!$B$5:$B$2004,G$4,Lançamentos!$G$5:$G$2004,$A15) -> 0 | H15: =SUMIFS(Lançamentos!$D$5:$D$2004,Lançamentos!$B$5:$B$2004,H$4,Lançamentos!$G$5:$G$2004,$A15) -> 0 | I15: =SUMIFS(Lançamentos!$D$5:$D$2004,Lançamentos!$B$5:$B$2004,I$4,Lançamentos!$G$5:$G$2004,$A15) -> 0 | J15: =SUMIFS(Lançamentos!$D$5:$D$2004,Lançamentos!$B$5:$B$2004,J$4,Lançamentos!$G$5:$G$2004,$A15) -> 0 | K15: =SUMIFS(Lançamentos!$D$5:$D$2004,Lançamentos!$B$5:$B$2004,K$4,Lançamentos!$G$5:$G$2004,$A15) -> 0 | L15: =SUMIFS(Lançamentos!$D$5:$D$2004,Lançamentos!$B$5:$B$2004,L$4,Lançamentos!$G$5:$G$2004,$A15) -> 0 | M15: =SUMIFS(Lançamentos!$D$5:$D$2004,Lançamentos!$B$5:$B$2004,M$4,Lançamentos!$G$5:$G$2004,$A15) -> 0 | ... R15: =SUMIFS(Lançamentos!$D$5:$D$2004,Lançamentos!$B$5:$B$2004,R$4,Lançamentos!$G$5:$G$2004,$A15) -> 0
A16: =A15+7 -> 46370 | B16: =A16+6 -> 46376 | C16: =SUMIFS(Lançamentos!$D$5:$D$2004,Lançamentos!$F$5:$F$2004,"Ganho",Lançamentos!$G$5:$G$2004,$A16) -> 0 | D16: =SUMIFS(Lançamentos!$D$5:$D$2004,Lançamentos!$F$5:$F$2004,"Gasto",Lançamentos!$G$5:$G$2004,$A16) -> 0 | E16: =C16-D16 -> 0 | F16: =SUMIFS(Lançamentos!$D$5:$D$2004,Lançamentos!$B$5:$B$2004,F$4,Lançamentos!$G$5:$G$2004,$A16) -> 0 | G16: =SUMIFS(Lançamentos!$D$5:$D$2004,Lançamentos!$B$5:$B$2004,G$4,Lançamentos!$G$5:$G$2004,$A16) -> 0 | H16: =SUMIFS(Lançamentos!$D$5:$D$2004,Lançamentos!$B$5:$B$2004,H$4,Lançamentos!$G$5:$G$2004,$A16) -> 0 | I16: =SUMIFS(Lançamentos!$D$5:$D$2004,Lançamentos!$B$5:$B$2004,I$4,Lançamentos!$G$5:$G$2004,$A16) -> 0 | J16: =SUMIFS(Lançamentos!$D$5:$D$2004,Lançamentos!$B$5:$B$2004,J$4,Lançamentos!$G$5:$G$2004,$A16) -> 0 | K16: =SUMIFS(Lançamentos!$D$5:$D$2004,Lançamentos!$B$5:$B$2004,K$4,Lançamentos!$G$5:$G$2004,$A16) -> 0 | L16: =SUMIFS(Lançamentos!$D$5:$D$2004,Lançamentos!$B$5:$B$2004,L$4,Lançamentos!$G$5:$G$2004,$A16) -> 0 | M16: =SUMIFS(Lançamentos!$D$5:$D$2004,Lançamentos!$B$5:$B$2004,M$4,Lançamentos!$G$5:$G$2004,$A16) -> 0 | ... R16: =SUMIFS(Lançamentos!$D$5:$D$2004,Lançamentos!$B$5:$B$2004,R$4,Lançamentos!$G$5:$G$2004,$A16) -> 0
A17: =A16+7 -> 46377 | B17: =A17+6 -> 46383 | C17: =SUMIFS(Lançamentos!$D$5:$D$2004,Lançamentos!$F$5:$F$2004,"Ganho",Lançamentos!$G$5:$G$2004,$A17) -> 0 | D17: =SUMIFS(Lançamentos!$D$5:$D$2004,Lançamentos!$F$5:$F$2004,"Gasto",Lançamentos!$G$5:$G$2004,$A17) -> 0 | E17: =C17-D17 -> 0 | F17: =SUMIFS(Lançamentos!$D$5:$D$2004,Lançamentos!$B$5:$B$2004,F$4,Lançamentos!$G$5:$G$2004,$A17) -> 0 | G17: =SUMIFS(Lançamentos!$D$5:$D$2004,Lançamentos!$B$5:$B$2004,G$4,Lançamentos!$G$5:$G$2004,$A17) -> 0 | H17: =SUMIFS(Lançamentos!$D$5:$D$2004,Lançamentos!$B$5:$B$2004,H$4,Lançamentos!$G$5:$G$2004,$A17) -> 0 | I17: =SUMIFS(Lançamentos!$D$5:$D$2004,Lançamentos!$B$5:$B$2004,I$4,Lançamentos!$G$5:$G$2004,$A17) -> 0 | J17: =SUMIFS(Lançamentos!$D$5:$D$2004,Lançamentos!$B$5:$B$2004,J$4,Lançamentos!$G$5:$G$2004,$A17) -> 0 | K17: =SUMIFS(Lançamentos!$D$5:$D$2004,Lançamentos!$B$5:$B$2004,K$4,Lançamentos!$G$5:$G$2004,$A17) -> 0 | L17: =SUMIFS(Lançamentos!$D$5:$D$2004,Lançamentos!$B$5:$B$2004,L$4,Lançamentos!$G$5:$G$2004,$A17) -> 0 | M17: =SUMIFS(Lançamentos!$D$5:$D$2004,Lançamentos!$B$5:$B$2004,M$4,Lançamentos!$G$5:$G$2004,$A17) -> 0 | ... R17: =SUMIFS(Lançamentos!$D$5:$D$2004,Lançamentos!$B$5:$B$2004,R$4,Lançamentos!$G$5:$G$2004,$A17) -> 0
... A57: =A56+7 -> 46657 | B57: =A57+6 -> 46663 | C57: =SUMIFS(Lançamentos!$D$5:$D$2004,Lançamentos!$F$5:$F$2004,"Ganho",Lançamentos!$G$5:$G$2004,$A57) -> 0 | D57: =SUMIFS(Lançamentos!$D$5:$D$2004,Lançamentos!$F$5:$F$2004,"Gasto",Lançamentos!$G$5:$G$2004,$A57) -> 0 | E57: =C57-D57 -> 0 | F57: =SUMIFS(Lançamentos!$D$5:$D$2004,Lançamentos!$B$5:$B$2004,F$4,Lançamentos!$G$5:$G$2004,$A57) -> 0 | G57: =SUMIFS(Lançamentos!$D$5:$D$2004,Lançamentos!$B$5:$B$2004,G$4,Lançamentos!$G$5:$G$2004,$A57) -> 0 | H57: =SUMIFS(Lançamentos!$D$5:$D$2004,Lançamentos!$B$5:$B$2004,H$4,Lançamentos!$G$5:$G$2004,$A57) -> 0 | I57: =SUMIFS(Lançamentos!$D$5:$D$2004,Lançamentos!$B$5:$B$2004,I$4,Lançamentos!$G$5:$G$2004,$A57) -> 0 | J57: =SUMIFS(Lançamentos!$D$5:$D$2004,Lançamentos!$B$5:$B$2004,J$4,Lançamentos!$G$5:$G$2004,$A57) -> 0 | K57: =SUMIFS(Lançamentos!$D$5:$D$2004,Lançamentos!$B$5:$B$2004,K$4,Lançamentos!$G$5:$G$2004,$A57) -> 0 | L57: =SUMIFS(Lançamentos!$D$5:$D$2004,Lançamentos!$B$5:$B$2004,L$4,Lançamentos!$G$5:$G$2004,$A57) -> 0 | M57: =SUMIFS(Lançamentos!$D$5:$D$2004,Lançamentos!$B$5:$B$2004,M$4,Lançamentos!$G$5:$G$2004,$A57) -> 0 | ... R57: =SUMIFS(Lançamentos!$D$5:$D$2004,Lançamentos!$B$5:$B$2004,R$4,Lançamentos!$G$5:$G$2004,$A57) -> 0
